{
    "CreateObject": {
        "prefix": "CreateObject",
        "body": "CreateObject(\"$1\")",
        "description": "Creates a new instance of the specified BrightScript component."
    },

    "ifAppInfo": {
        "prefix": "ifAppInfo",
        "body": "ifAppInfo",
        "description": "Implemented By:\nroAppInfo\n"
    },
    "ifAppManager": {
        "prefix": "ifAppManager",
        "body": "ifAppManager",
        "description": "Implemented By:\nroAppManager\n"
    },
    "ifArray": {
        "prefix": "ifArray",
        "body": "ifArray",
        "description": "Implemented By:\nroArray\nroByteArray\nroList\nroXMLList\n"
    },
    "ifArrayJoin": {
        "prefix": "ifArrayJoin",
        "body": "ifArrayJoin",
        "description": "Implemented By:\nroArray\n"
    },
    "ifArraySort": {
        "prefix": "ifArraySort",
        "body": "ifArraySort",
        "description": "Implemented By:\nroArray\n"
    },
    "ifAssociativeArray": {
        "prefix": "ifAssociativeArray",
        "body": "ifAssociativeArray",
        "description": "Implemented By:\nroAssociativeArray\nroSGNode\n"
    }
}
